[1,["d5VkiLwetPHbD2WqSoQ9sH"],["_textureSetter"],["cc.SpriteFrame"],0,[[[{"name":"spine_forestman_bg=eff23","rect":[285,437,140,72],"offset":[0,0],"originalSize":[140,72],"capInsets":[0,0,0,0]}],[0],0,[0],[0],[0]],[[{"name":"spine_forestman_bg=eff28","rect":[285,807,140,72],"offset":[0,0],"originalSize":[140,72],"capInsets":[0,0,0,0]}],[0],0,[0],[0],[0]],[[{"name":"spine_forestman_bg=eff18","rect":[143,738,140,72],"offset":[0,0],"originalSize":[140,72],"capInsets":[0,0,0,0]}],[0],0,[0],[0],[0]],[[{"name":"spine_forestman_bg=fengye","rect":[351,223,16,34],"offset":[0,0],"originalSize":[16,34],"capInsets":[0,0,0,0]}],[0],0,[0],[0],[0]],[[{"name":"spine_forestman_bg=eff06","rect":[1,738,140,72],"offset":[0,0],"originalSize":[140,72],"capInsets":[0,0,0,0]}],[0],0,[0],[0],[0]],[[{"name":"spine_forestman_bg=eff15","rect":[143,516,140,72],"offset":[0,0],"originalSize":[140,72],"capInsets":[0,0,0,0]}],[0],0,[0],[0],[0]],[[{"name":"spine_forestman_bg=eff05","rect":[1,664,140,72],"offset":[0,0],"originalSize":[140,72],"capInsets":[0,0,0,0]}],[0],0,[0],[0],[0]],[[{"name":"spine_forestman_bg=eff09","rect":[143,294,140,72],"offset":[0,0],"originalSize":[140,72],"capInsets":[0,0,0,0]}],[0],0,[0],[0],[0]],[[{"name":"spine_forestman_bg=eff26","rect":[285,659,140,72],"offset":[0,0],"originalSize":[140,72],"capInsets":[0,0,0,0]}],[0],0,[0],[0],[0]],[[{"name":"spine_forestman_bg=eff19","rect":[143,812,140,72],"offset":[0,0],"originalSize":[140,72],"capInsets":[0,0,0,0]}],[0],0,[0],[0],[0]],[[{"name":"spine_forestman_bg=eff21","rect":[285,289,140,72],"offset":[0,0],"originalSize":[140,72],"capInsets":[0,0,0,0]}],[0],0,[0],[0],[0]],[[{"name":"spine_forestman_bg=eff24","rect":[285,511,140,72],"offset":[0,0],"originalSize":[140,72],"capInsets":[0,0,0,0]}],[0],0,[0],[0],[0]],[[{"name":"spine_forestman_bg=eff01","rect":[1,368,140,72],"offset":[0,0],"originalSize":[140,72],"capInsets":[0,0,0,0]}],[0],0,[0],[0],[0]],[[{"name":"spine_forestman_bg=eff13","rect":[143,368,140,72],"offset":[0,0],"originalSize":[140,72],"capInsets":[0,0,0,0]}],[0],0,[0],[0],[0]],[[{"name":"spine_forestman_bg=eff20","rect":[143,886,140,72],"offset":[0,0],"originalSize":[140,72],"capInsets":[0,0,0,0]}],[0],0,[0],[0],[0]],[[{"name":"spine_forestman_bg=eff29","rect":[285,881,140,72],"offset":[0,0],"originalSize":[140,72],"capInsets":[0,0,0,0]}],[0],0,[0],[0],[0]],[[{"name":"spine_forestman_bg=eff02","rect":[1,442,140,72],"offset":[0,0],"originalSize":[140,72],"capInsets":[0,0,0,0]}],[0],0,[0],[0],[0]],[[{"name":"spine_forestman_bg=kuye","rect":[319,223,30,63],"offset":[0,0],"originalSize":[30,63],"capInsets":[0,0,0,0]}],[0],0,[0],[0],[0]],[[{"name":"spine_forestman_bg=eff04","rect":[1,590,140,72],"offset":[0,0],"originalSize":[140,72],"capInsets":[0,0,0,0]}],[0],0,[0],[0],[0]],[[{"name":"spine_forestman_bg=eff27","rect":[285,733,140,72],"offset":[0,0],"originalSize":[140,72],"capInsets":[0,0,0,0]}],[0],0,[0],[0],[0]],[[{"name":"spine_forestman_bg=eff12","rect":[253,149,140,72],"offset":[0,0],"originalSize":[140,72],"capInsets":[0,0,0,0]}],[0],0,[0],[0],[0]],[[{"name":"spine_forestman_bg=eff10","rect":[253,1,140,72],"offset":[0,0],"originalSize":[140,72],"capInsets":[0,0,0,0]}],[0],0,[0],[0],[0]],[[{"name":"spine_forestman_bg=eff11","rect":[253,75,140,72],"offset":[0,0],"originalSize":[140,72],"capInsets":[0,0,0,0]}],[0],0,[0],[0],[0]],[[{"name":"spine_forestman_bg=dian","rect":[253,223,64,64],"offset":[0,0],"originalSize":[64,64],"capInsets":[0,0,0,0]}],[0],0,[0],[0],[0]],[[{"name":"spine_forestman_bg=eff07","rect":[1,812,140,72],"offset":[0,0],"originalSize":[140,72],"capInsets":[0,0,0,0]}],[0],0,[0],[0],[0]],[[{"name":"spine_forestman_bg=eff25","rect":[285,585,140,72],"offset":[0,0],"originalSize":[140,72],"capInsets":[0,0,0,0]}],[0],0,[0],[0],[0]],[[{"name":"spine_forestman_bg=eff03","rect":[1,516,140,72],"offset":[0,0],"originalSize":[140,72],"capInsets":[0,0,0,0]}],[0],0,[0],[0],[0]],[[{"name":"spine_forestman_bg=eff16","rect":[143,590,140,72],"offset":[0,0],"originalSize":[140,72],"capInsets":[0,0,0,0]}],[0],0,[0],[0],[0]],[[{"name":"spine_forestman_bg=eff08","rect":[1,886,140,72],"offset":[0,0],"originalSize":[140,72],"capInsets":[0,0,0,0]}],[0],0,[0],[0],[0]],[[{"name":"spine_forestman_bg=eff17","rect":[143,664,140,72],"offset":[0,0],"originalSize":[140,72],"capInsets":[0,0,0,0]}],[0],0,[0],[0],[0]],[[{"name":"spine_forestman_bg=guangyun","rect":[1,1,250,291],"offset":[0,0],"originalSize":[250,291],"capInsets":[0,0,0,0]}],[0],0,[0],[0],[0]],[[{"name":"spine_forestman_bg=eff14","rect":[143,442,140,72],"offset":[0,0],"originalSize":[140,72],"capInsets":[0,0,0,0]}],[0],0,[0],[0],[0]],[[{"name":"spine_forestman_bg=eff22","rect":[285,363,140,72],"offset":[0,0],"originalSize":[140,72],"capInsets":[0,0,0,0]}],[0],0,[0],[0],[0]],[[{"name":"spine_forestman_bg=eff00","rect":[1,294,140,72],"offset":[0,0],"originalSize":[140,72],"capInsets":[0,0,0,0]}],[0],0,[0],[0],[0]]]]