[1,["a60KzKkDFN3avxVsg6VJKG"],["spriteFrame"],[["cc.BitmapFont",["_name","fontSize","_fntConfig"],0]],[[0,0,1,2,4]],[[0,"ui_font=font08",32,{"commonHeight":110,"fontSize":32,"atlasName":"ui_font=font08.webp","fontDefDictionary":{"9":{"xOffset":0,"yOffset":0,"xAdvance":144,"rect":{"x":0,"y":0,"width":0,"height":0}},"32":{"xOffset":0,"yOffset":0,"xAdvance":18,"rect":{"x":0,"y":0,"width":0,"height":0}},"33":{"xOffset":0,"yOffset":15,"xAdvance":30,"rect":{"x":719,"y":205,"width":40,"height":95}},"34":{"xOffset":0,"yOffset":15,"xAdvance":52,"rect":{"x":171,"y":424,"width":62,"height":54}},"35":{"xOffset":0,"yOffset":19,"xAdvance":61,"rect":{"x":389,"y":695,"width":71,"height":86}},"36":{"xOffset":0,"yOffset":5,"xAdvance":57,"rect":{"x":532,"y":389,"width":67,"height":117}},"37":{"xOffset":0,"yOffset":14,"xAdvance":72,"rect":{"x":0,"y":578,"width":82,"height":96}},"38":{"xOffset":0,"yOffset":13,"xAdvance":68,"rect":{"x":92,"y":386,"width":78,"height":98}},"39":{"xOffset":0,"yOffset":15,"xAdvance":29,"rect":{"x":728,"y":0,"width":39,"height":54}},"40":{"xOffset":0,"yOffset":9,"xAdvance":34,"rect":{"x":717,"y":301,"width":44,"height":107}},"41":{"xOffset":0,"yOffset":9,"xAdvance":34,"rect":{"x":717,"y":409,"width":44,"height":107}},"42":{"xOffset":0,"yOffset":14,"xAdvance":53,"rect":{"x":468,"y":293,"width":63,"height":62}},"43":{"xOffset":0,"yOffset":37,"xAdvance":52,"rect":{"x":240,"y":625,"width":62,"height":63}},"44":{"xOffset":0,"yOffset":71,"xAdvance":31,"rect":{"x":614,"y":193,"width":41,"height":54}},"45":{"xOffset":0,"yOffset":52,"xAdvance":45,"rect":{"x":322,"y":381,"width":55,"height":37}},"46":{"xOffset":0,"yOffset":70,"xAdvance":29,"rect":{"x":719,"y":611,"width":39,"height":40}},"47":{"xOffset":0,"yOffset":9,"xAdvance":44,"rect":{"x":664,"y":548,"width":54,"height":107}},"48":{"xOffset":0,"yOffset":13,"xAdvance":62,"rect":{"x":389,"y":596,"width":72,"height":98}},"49":{"xOffset":0,"yOffset":15,"xAdvance":55,"rect":{"x":556,"y":0,"width":65,"height":95}},"50":{"xOffset":0,"yOffset":14,"xAdvance":59,"rect":{"x":462,"y":452,"width":69,"height":96}},"51":{"xOffset":0,"yOffset":13,"xAdvance":59,"rect":{"x":462,"y":549,"width":69,"height":98}},"52":{"xOffset":0,"yOffset":15,"xAdvance":64,"rect":{"x":269,"y":96,"width":74,"height":95}},"53":{"xOffset":0,"yOffset":15,"xAdvance":56,"rect":{"x":532,"y":603,"width":66,"height":96}},"54":{"xOffset":0,"yOffset":13,"xAdvance":60,"rect":{"x":417,"y":0,"width":70,"height":98}},"55":{"xOffset":0,"yOffset":15,"xAdvance":58,"rect":{"x":479,"y":99,"width":68,"height":95}},"56":{"xOffset":0,"yOffset":13,"xAdvance":62,"rect":{"x":344,"y":80,"width":72,"height":98}},"57":{"xOffset":0,"yOffset":14,"xAdvance":60,"rect":{"x":461,"y":695,"width":70,"height":97}},"58":{"xOffset":0,"yOffset":32,"xAdvance":29,"rect":{"x":674,"y":106,"width":39,"height":78}},"59":{"xOffset":0,"yOffset":32,"xAdvance":31,"rect":{"x":719,"y":517,"width":41,"height":93}},"60":{"xOffset":0,"yOffset":36,"xAdvance":50,"rect":{"x":315,"y":725,"width":60,"height":65}},"61":{"xOffset":0,"yOffset":40,"xAdvance":50,"rect":{"x":417,"y":99,"width":60,"height":56}},"62":{"xOffset":0,"yOffset":36,"xAdvance":50,"rect":{"x":600,"y":374,"width":60,"height":65}},"63":{"xOffset":0,"yOffset":13,"xAdvance":51,"rect":{"x":600,"y":276,"width":61,"height":97}},"64":{"xOffset":0,"yOffset":6,"xAdvance":117,"rect":{"x":0,"y":0,"width":127,"height":129}},"65":{"xOffset":0,"yOffset":15,"xAdvance":73,"rect":{"x":0,"y":482,"width":83,"height":95}},"66":{"xOffset":0,"yOffset":14,"xAdvance":64,"rect":{"x":240,"y":526,"width":74,"height":97}},"67":{"xOffset":0,"yOffset":14,"xAdvance":58,"rect":{"x":479,"y":195,"width":68,"height":97}},"68":{"xOffset":0,"yOffset":14,"xAdvance":65,"rect":{"x":163,"y":701,"width":75,"height":97}},"69":{"xOffset":0,"yOffset":15,"xAdvance":57,"rect":{"x":532,"y":507,"width":67,"height":95}},"70":{"xOffset":0,"yOffset":15,"xAdvance":56,"rect":{"x":532,"y":700,"width":66,"height":95}},"71":{"xOffset":0,"yOffset":14,"xAdvance":62,"rect":{"x":389,"y":498,"width":72,"height":97}},"72":{"xOffset":0,"yOffset":15,"xAdvance":65,"rect":{"x":205,"y":0,"width":75,"height":95}},"73":{"xOffset":0,"yOffset":15,"xAdvance":29,"rect":{"x":760,"y":154,"width":39,"height":95}},"74":{"xOffset":0,"yOffset":15,"xAdvance":48,"rect":{"x":615,"y":96,"width":58,"height":96}},"75":{"xOffset":0,"yOffset":15,"xAdvance":65,"rect":{"x":183,"y":226,"width":75,"height":95}},"76":{"xOffset":0,"yOffset":15,"xAdvance":55,"rect":{"x":548,"y":180,"width":65,"height":95}},"77":{"xOffset":0,"yOffset":15,"xAdvance":81,"rect":{"x":0,"y":386,"width":91,"height":95}},"78":{"xOffset":0,"yOffset":15,"xAdvance":68,"rect":{"x":104,"y":226,"width":78,"height":95}},"79":{"xOffset":0,"yOffset":13,"xAdvance":66,"rect":{"x":128,"y":0,"width":76,"height":98}},"80":{"xOffset":0,"yOffset":14,"xAdvance":62,"rect":{"x":334,"y":192,"width":72,"height":96}},"81":{"xOffset":0,"yOffset":13,"xAdvance":66,"rect":{"x":163,"y":588,"width":76,"height":112}},"82":{"xOffset":0,"yOffset":14,"xAdvance":64,"rect":{"x":247,"y":322,"width":74,"height":96}},"83":{"xOffset":0,"yOffset":14,"xAdvance":57,"rect":{"x":488,"y":0,"width":67,"height":97}},"84":{"xOffset":0,"yOffset":15,"xAdvance":61,"rect":{"x":390,"y":381,"width":71,"height":95}},"85":{"xOffset":0,"yOffset":15,"xAdvance":64,"rect":{"x":259,"y":203,"width":74,"height":96}},"86":{"xOffset":0,"yOffset":15,"xAdvance":72,"rect":{"x":0,"y":675,"width":82,"height":95}},"87":{"xOffset":0,"yOffset":15,"xAdvance":104,"rect":{"x":0,"y":130,"width":114,"height":95}},"88":{"xOffset":0,"yOffset":15,"xAdvance":69,"rect":{"x":83,"y":578,"width":79,"height":95}},"89":{"xOffset":0,"yOffset":15,"xAdvance":67,"rect":{"x":115,"y":130,"width":77,"height":95}},"90":{"xOffset":0,"yOffset":15,"xAdvance":57,"rect":{"x":532,"y":293,"width":67,"height":95}},"91":{"xOffset":0,"yOffset":10,"xAdvance":37,"rect":{"x":716,"y":656,"width":47,"height":105}},"92":{"xOffset":0,"yOffset":9,"xAdvance":44,"rect":{"x":662,"y":301,"width":54,"height":107}},"93":{"xOffset":0,"yOffset":10,"xAdvance":37,"rect":{"x":680,"y":0,"width":47,"height":105}},"94":{"xOffset":0,"yOffset":15,"xAdvance":55,"rect":{"x":104,"y":322,"width":65,"height":53}},"95":{"xOffset":0,"yOffset":93,"xAdvance":69,"rect":{"x":83,"y":674,"width":79,"height":37}},"96":{"xOffset":0,"yOffset":4,"xAdvance":33,"rect":{"x":600,"y":548,"width":43,"height":42}},"97":{"xOffset":0,"yOffset":31,"xAdvance":61,"rect":{"x":396,"y":289,"width":71,"height":80}},"98":{"xOffset":0,"yOffset":12,"xAdvance":63,"rect":{"x":315,"y":625,"width":73,"height":99}},"99":{"xOffset":0,"yOffset":31,"xAdvance":54,"rect":{"x":599,"y":682,"width":64,"height":81}},"100":{"xOffset":0,"yOffset":12,"xAdvance":65,"rect":{"x":239,"y":701,"width":75,"height":99}},"101":{"xOffset":0,"yOffset":31,"xAdvance":59,"rect":{"x":462,"y":370,"width":69,"height":81}},"102":{"xOffset":0,"yOffset":9,"xAdvance":48,"rect":{"x":600,"y":440,"width":58,"height":101}},"103":{"xOffset":0,"yOffset":31,"xAdvance":65,"rect":{"x":193,"y":99,"width":75,"height":103}},"104":{"xOffset":0,"yOffset":12,"xAdvance":61,"rect":{"x":407,"y":179,"width":71,"height":98}},"105":{"xOffset":0,"yOffset":12,"xAdvance":30,"rect":{"x":719,"y":106,"width":40,"height":98}},"106":{"xOffset":0,"yOffset":12,"xAdvance":41,"rect":{"x":664,"y":656,"width":51,"height":122}},"107":{"xOffset":0,"yOffset":12,"xAdvance":63,"rect":{"x":315,"y":526,"width":73,"height":98}},"108":{"xOffset":0,"yOffset":12,"xAdvance":29,"rect":{"x":760,"y":55,"width":39,"height":98}},"109":{"xOffset":0,"yOffset":30,"xAdvance":93,"rect":{"x":0,"y":226,"width":103,"height":80}},"110":{"xOffset":0,"yOffset":30,"xAdvance":63,"rect":{"x":322,"y":300,"width":73,"height":80}},"111":{"xOffset":0,"yOffset":31,"xAdvance":63,"rect":{"x":84,"y":485,"width":73,"height":80}},"112":{"xOffset":0,"yOffset":31,"xAdvance":65,"rect":{"x":171,"y":322,"width":75,"height":101}},"113":{"xOffset":0,"yOffset":31,"xAdvance":65,"rect":{"x":240,"y":424,"width":75,"height":101}},"114":{"xOffset":0,"yOffset":31,"xAdvance":51,"rect":{"x":355,"y":0,"width":61,"height":79}},"115":{"xOffset":0,"yOffset":31,"xAdvance":56,"rect":{"x":548,"y":98,"width":66,"height":81}},"116":{"xOffset":0,"yOffset":19,"xAdvance":47,"rect":{"x":622,"y":0,"width":57,"height":93}},"117":{"xOffset":0,"yOffset":32,"xAdvance":63,"rect":{"x":281,"y":0,"width":73,"height":79}},"118":{"xOffset":0,"yOffset":32,"xAdvance":66,"rect":{"x":83,"y":712,"width":76,"height":78}},"119":{"xOffset":0,"yOffset":32,"xAdvance":93,"rect":{"x":0,"y":307,"width":103,"height":78}},"120":{"xOffset":0,"yOffset":32,"xAdvance":63,"rect":{"x":316,"y":419,"width":73,"height":78}},"121":{"xOffset":0,"yOffset":32,"xAdvance":66,"rect":{"x":163,"y":485,"width":76,"height":102}},"122":{"xOffset":0,"yOffset":32,"xAdvance":54,"rect":{"x":599,"y":603,"width":64,"height":78}},"123":{"xOffset":0,"yOffset":9,"xAdvance":47,"rect":{"x":659,"y":440,"width":57,"height":107}},"124":{"xOffset":0,"yOffset":9,"xAdvance":24,"rect":{"x":761,"y":517,"width":34,"height":123}},"125":{"xOffset":0,"yOffset":9,"xAdvance":46,"rect":{"x":662,"y":193,"width":56,"height":107}},"126":{"xOffset":0,"yOffset":47,"xAdvance":50,"rect":{"x":462,"y":648,"width":60,"height":39}}},"kerningDict":{}}]],0,0,[0],[0],[0]]